random_names_spanish/__init__.py
random_names_spanish/functions.py
random_names_spanish-1.0.dist-info/METADATA
random_names_spanish-1.0.dist-info/WHEEL
random_names_spanish-1.0.dist-info/top_level.txt
random_names_spanish-1.0.dist-info/RECORD
