Metadata-Version: 2.1
Name: random-names-spanish
Version: 1.0
Summary: Generador de nombres aleatorios en español, tanto masculinos como femeninos.
Home-page: https://github.com/DavichoStar
Author: DavichoStar
Author-email: davichostar@protonmail.com
License: MIT
Requires-Dist: pandas
